PersonAS/__init__.py
PersonAS/first_page.py
PersonAS/second_page.py
Person_Anirban_details-0.1.dist-info/METADATA
Person_Anirban_details-0.1.dist-info/WHEEL
Person_Anirban_details-0.1.dist-info/top_level.txt
Person_Anirban_details-0.1.dist-info/RECORD
