Metadata-Version: 2.1
Name: Person_Anirban_details
Version: 0.1
Summary: Testing the basics of PyPi packages.
Author: Anirban Saha
Author-email: <mailme@anirbansaha.com>
Keywords: python,Anirban Saha
Classifier: Development Status :: 1 - Planning
Classifier: Intended Audience :: Developers
Classifier: Programming Language :: Python :: 3
Classifier: Operating System :: Unix
Classifier: Operating System :: MacOS :: MacOS X
Classifier: Operating System :: Microsoft :: Windows
